flow_py_sdk/__init__.py
flow_py_sdk/account_key.py
flow_py_sdk/cadence/__init__.py
flow_py_sdk/cadence/address.py
flow_py_sdk/cadence/composite.py
flow_py_sdk/cadence/constants.py
flow_py_sdk/cadence/decode.py
flow_py_sdk/cadence/encode.py
flow_py_sdk/cadence/kind.py
flow_py_sdk/cadence/kinds.py
flow_py_sdk/cadence/simple_kinds.py
flow_py_sdk/cadence/types.py
flow_py_sdk/cadence/value.py
flow_py_sdk/client/__init__.py
flow_py_sdk/client/client.py
flow_py_sdk/client/entities.py
flow_py_sdk/exceptions.py
flow_py_sdk/frlp/__init__.py
flow_py_sdk/frlp/utils.py
flow_py_sdk/proto/__init__.py
flow_py_sdk/proto/flow/__init__.py
flow_py_sdk/proto/flow/access.py
flow_py_sdk/proto/flow/entities.py
flow_py_sdk/proto/flow/execution.py
flow_py_sdk/script.py
flow_py_sdk/signer/__init__.py
flow_py_sdk/signer/hash_algo.py
flow_py_sdk/signer/in_memory_signer.py
flow_py_sdk/signer/in_memory_verifier.py
flow_py_sdk/signer/sign_algo.py
flow_py_sdk/signer/signer.py
flow_py_sdk/signer/verifier.py
flow_py_sdk/templates.py
flow_py_sdk/tx.py
flow_py_sdk/utils/__init__.py
flow_py_sdk/utils/verify_user_signature.py
flow_py_sdk-2.0.2.dist-info/entry_points.txt
flow_py_sdk-2.0.2.dist-info/LICENSE
flow_py_sdk-2.0.2.dist-info/WHEEL
flow_py_sdk-2.0.2.dist-info/METADATA
flow_py_sdk-2.0.2.dist-info/RECORD
