Metadata-Version: 2.1
Name: flow-py-sdk
Version: 2.0.2
Summary: A python SKD for the flow blockchain
Home-page: https://github.com/janezpodhostnik/flow-py-sdk
License: MIT
Author: Janez Podhostnik
Author-email: janez.podhostnik@gmail.com
Requires-Python: >=3.9,<4.0
Classifier: License :: OSI Approved :: MIT License
Classifier: Programming Language :: Python :: 3
Classifier: Programming Language :: Python :: 3.9
Classifier: Programming Language :: Python :: 3.10
Classifier: Programming Language :: Python :: 3.11
Requires-Dist: betterproto[compiler] (==v2.0.0-beta6)
Requires-Dist: ecdsa (>=v0.19,<0.20)
Requires-Dist: grpcio-tools (>=1.65,<2.0)
Requires-Dist: grpclib (>=0.4,<0.5)
Requires-Dist: rlp (>=4.0,<5.0)
Project-URL: Repository, https://github.com/janezpodhostnik/flow-py-sdk
